tiled_viewer/TiledViewer.py
tiled_viewer/__init__.py
tiled_viewer/_imports_.py
tiled_viewer/metadata.json
tiled_viewer/package-info.json
tiled_viewer/tiled_viewer.min.js
tiled_viewer/tiled_viewer.min.js.map
tiled_viewer-0.0.13.dist-info/licenses/LICENSE
tiled_viewer-0.0.13.dist-info/METADATA
tiled_viewer-0.0.13.dist-info/WHEEL
tiled_viewer-0.0.13.dist-info/top_level.txt
tiled_viewer-0.0.13.dist-info/RECORD
