Metadata-Version: 2.4
Name: tiled_viewer
Version: 0.0.13
Summary: A viewer tool for Bluesky Tiled servers
Author: Seij De Leon <seijdeleon@lbl.gov>
License: BSD
Classifier: Framework :: Dash
License-File: LICENSE
Dynamic: author
Dynamic: classifier
Dynamic: description
Dynamic: description-content-type
Dynamic: license
Dynamic: license-file
Dynamic: summary
